<?xml version="1.0" encoding="UTF-8"?>
<con:testCase id="f8d9c04f-3370-4394-990f-e7a17fd94e3c" discardOkResults="true" failOnError="true" failTestCaseOnErrors="true" keepSession="false" name="TestCase 2" searchProperties="true" xmlns:con="http://eviware.com/soapui/config"><con:settings><con:setting id="f8d9c04f-3370-4394-990f-e7a17fd94e3cfileName">TestCase-2</con:setting></con:settings><con:savedRecentRuns>1</con:savedRecentRuns><con:testStep type="groovy" name="Groovy Script" id="92eb7ca2-e6f0-424b-9528-d9c2ae7df292"><con:settings/><con:config><script/></con:config></con:testStep><con:properties/><con:reportParameters/></con:testCase>